gym_chrome_dino/__init__.py
gym_chrome_dino/envs/__init__.py
gym_chrome_dino/envs/chrome_dino_env.py
gym_chrome_dino/game/__init__.py
gym_chrome_dino/game/dino_game.py
gym_chrome_dino/utils/__init__.py
gym_chrome_dino/utils/atari_wrappers.py
gym_chrome_dino/utils/helpers.py
gym_chrome_dino/utils/wrappers.py
gym_chrome_dino-0.0.3.dist-info/DESCRIPTION.rst
gym_chrome_dino-0.0.3.dist-info/METADATA
gym_chrome_dino-0.0.3.dist-info/RECORD
gym_chrome_dino-0.0.3.dist-info/WHEEL
gym_chrome_dino-0.0.3.dist-info/metadata.json
gym_chrome_dino-0.0.3.dist-info/top_level.txt
