Metadata-Version: 2.0
Name: gym-chrome-dino
Version: 0.0.3
Summary: Chrome Dino in OpenAI Gym
Home-page: https://github.com/elvisyjlin/gym-chrome-dino
Author: Elvis Yu-Jing Lin
Author-email: elvisyjlin@gmail.com
License: MIT
Platform: UNKNOWN
Classifier: Programming Language :: Python :: 3
Classifier: License :: OSI Approved :: MIT License
Classifier: Operating System :: OS Independent
Requires-Dist: Pillow (>=3.1.2)
Requires-Dist: beautifulsoup4 (>=4.4.1)
Requires-Dist: gym (>=0.10.8)
Requires-Dist: lxml (>=3.5.0)
Requires-Dist: numpy (>=1.15.3)
Requires-Dist: opencv-python (>=3.4.2.17)
Requires-Dist: requests (>=2.9.1)
Requires-Dist: selenium (>=3.14.1)
